hiti_preproc/__init__.py
hiti_preproc/dicoms.py
hiti_preproc/rois.py
hiti_preproc-0.2.3.dist-info/METADATA
hiti_preproc-0.2.3.dist-info/WHEEL
hiti_preproc-0.2.3.dist-info/top_level.txt
hiti_preproc-0.2.3.dist-info/RECORD
